{
    "J": [
        [
            1,
            2
        ],
        [
            0,
            3
        ],
        [
            6,
            10
        ],
        [
            1,
            10
        ],
        [
            4,
            11
        ],
        [
            0,
            8
        ],
        [
            6,
            7
        ],
        [
            4,
            7
        ],
        [
            3
        ],
        [
            2,
            8
        ],
        [
            9,
            10
        ],
        [
            3,
            6
        ],
        [
            3,
            11
        ],
        [
            0,
            4
        ],
        [
            7,
            9
        ],
        [
            5,
            11
        ],
        [
            0,
            5
        ],
        [
            10
        ],
        [
            5,
            9
        ],
        [
            5,
            10
        ],
        [
            3,
            4
        ],
        [
            2,
            7
        ],
        [
            8,
            9
        ],
        [
            4,
            10
        ],
        [
            5,
            7
        ],
        [
            3,
            10
        ],
        [
            3,
            9
        ],
        [
            6,
            8
        ],
        [
            0,
            6
        ],
        [
            0
        ],
        [
            2,
            4
        ],
        [
            4,
            5
        ],
        [
            2,
            3
        ],
        [
            11
        ],
        [
            4,
            6
        ],
        [
            1,
            8
        ],
        [
            2,
            9
        ],
        [
            2
        ],
        [
            7
        ],
        [
            0,
            2
        ],
        [
            8,
            11
        ],
        [
            0,
            9
        ],
        [
            0,
            11
        ],
        [
            7,
            8
        ],
        [
            6,
            9
        ],
        [
            7,
            10
        ],
        [
            6
        ],
        [
            2,
            10
        ],
        [
            5,
            8
        ],
        [
            1,
            6
        ],
        [
            0,
            1
        ],
        [
            7,
            11
        ],
        [
            1,
            11
        ],
        [
            1,
            4
        ],
        [
            8,
            10
        ],
        [
            5
        ],
        [
            0,
            7
        ],
        [
            3,
            7
        ],
        [
            1,
            7
        ],
        [
            8
        ],
        [
            6,
            11
        ],
        [
            1,
            5
        ],
        [
            9,
            11
        ],
        [
            4
        ],
        [
            1
        ],
        [
            4,
            8
        ],
        [
            9
        ],
        [
            3,
            8
        ],
        [
            4,
            9
        ],
        [
            2,
            6
        ]
    ],
    "c": [
        9.775649074234785,
        9.622100584232525,
        8.638201643349955,
        -0.07212523346043254,
        1.99735430452183,
        1.24582525443238,
        10.818057805416045,
        9.436256000240384,
        10.677832529384164,
        -0.3446781576162803,
        9.458130564569379,
        9.534123165542258,
        9.28093499144484,
        0.7538459152870123,
        10.540143879774469,
        11.849773324912496,
        1.6953085305512219,
        -1.431053546855606,
        10.590449781798954,
        2.080718512977135,
        9.580087745419855,
        0.6636376283171092,
        8.644879034731662,
        2.142513087742588,
        -0.14261964992712461,
        9.897732224812962,
        1.3631974446397392,
        8.797396788314352,
        -0.16845889077683407,
        0.17225445751219715,
        10.652837020471464,
        1.4601157514305723,
        -0.17134135931634087,
        9.874432988989954,
        10.124008874862666,
        8.915671307990975,
        0.08987590106312793,
        0.9394525152714208,
        0.6018516974051762,
        1.878297786323936,
        8.988365243353416,
        0.591292442208629,
        9.716983700906004,
        11.213004097176315,
        0.4507012222185407,
        1.21522874531753,
        11.816721478839188,
        11.040907131825625,
        10.47101945348116,
        0.06502880958662105,
        10.375694415486347,
        1.8040687563984448,
        -1.0676522500217085,
        8.995206207985554,
        1.762281308533559,
        0.3443592293346849,
        9.305451236079039,
        10.32971925401,
        10.414590143776564,
        0.622212163429515,
        9.400326355276011,
        8.386196985178685,
        1.5729176141995298,
        1.893859152778252,
        10.86158414027496,
        2.592007877448383,
        -0.12341144625348233,
        0.8829686488154684,
        0.28361985743740903,
        0.8038534749884552
    ],
    "label": {
        "x": [
            1.0,
            0.0,
            0.0,
            0.0,
            1.0,
            1.0,
            0.0,
            1.0,
            1.0,
            0.0,
            1.0,
            0.0
        ],
        "z": [
            1.0,
            -1.0,
            -1.0,
            -1.0,
            1.0,
            1.0,
            -1.0,
            1.0,
            1.0,
            -1.0,
            1.0,
            -1.0
        ],
        "obj_val": -169.4076692936252
    }
}