{
    "J": [
        [
            4,
            9
        ],
        [
            2,
            10
        ],
        [
            8,
            9
        ],
        [
            5,
            7
        ],
        [
            5,
            8
        ],
        [
            2,
            5
        ],
        [
            2
        ],
        [
            0
        ],
        [
            6
        ],
        [
            8
        ],
        [
            2,
            8
        ],
        [
            7,
            10
        ],
        [
            3,
            7
        ],
        [
            3,
            5
        ],
        [
            2,
            11
        ],
        [
            6,
            8
        ],
        [
            7,
            9
        ],
        [
            0,
            1
        ],
        [
            2,
            9
        ],
        [
            1
        ],
        [
            4,
            10
        ],
        [
            2,
            7
        ],
        [
            1,
            10
        ],
        [
            6,
            10
        ],
        [
            8,
            11
        ],
        [
            7,
            8
        ],
        [
            10,
            11
        ],
        [
            3,
            11
        ],
        [
            1,
            9
        ],
        [
            1,
            8
        ],
        [
            9,
            11
        ],
        [
            4
        ],
        [
            2,
            4
        ],
        [
            3,
            9
        ],
        [
            4,
            11
        ],
        [
            0,
            7
        ],
        [
            2,
            6
        ],
        [
            3,
            4
        ],
        [
            7
        ],
        [
            6,
            7
        ],
        [
            7,
            11
        ],
        [
            4,
            5
        ],
        [
            8,
            10
        ],
        [
            0,
            10
        ],
        [
            1,
            4
        ],
        [
            0,
            6
        ],
        [
            4,
            7
        ],
        [
            0,
            9
        ],
        [
            4,
            6
        ],
        [
            3
        ],
        [
            10
        ],
        [
            1,
            5
        ],
        [
            1,
            6
        ],
        [
            3,
            6
        ],
        [
            5,
            11
        ],
        [
            2,
            3
        ],
        [
            3,
            10
        ],
        [
            11
        ],
        [
            5,
            9
        ],
        [
            1,
            3
        ],
        [
            1,
            7
        ],
        [
            0,
            8
        ],
        [
            9,
            10
        ],
        [
            4,
            8
        ],
        [
            1,
            2
        ],
        [
            0,
            2
        ],
        [
            0,
            3
        ],
        [
            0,
            4
        ],
        [
            5
        ],
        [
            9
        ]
    ],
    "c": [
        -4.262767817495328,
        -1.4132133302976135,
        2.609839528090399,
        0.8727888594742907,
        -3.392739668689151,
        -0.7403654616312396,
        -3.271807088510407,
        3.0914897799742143,
        -1.795393588376224,
        2.298607943252744,
        1.6881713110310876,
        4.461768428126028,
        3.350357442560373,
        2.266764815054449,
        -4.215380198357649,
        -3.144123604811834,
        4.467882946963872,
        -0.09549134918963009,
        0.2689255056724509,
        -0.4503516586362597,
        -2.2903673294631597,
        1.2374817678005847,
        4.581906666884368,
        0.08188769893606196,
        -3.2813375661156305,
        3.5443671429993824,
        -3.496622901599935,
        2.163363157284678,
        0.38012336245251444,
        -2.7487640469621812,
        -0.8387927413864347,
        3.3624917124827967,
        -2.531100543499586,
        2.880496032007443,
        1.9603053131308386,
        -0.5187474075787719,
        -2.0742602901681995,
        -4.7784216854449335,
        2.330855905929968,
        -2.0021972188135417,
        1.542091789770586,
        -1.4473943261738773,
        1.5808519122724505,
        -4.871042279226573,
        -1.6616144963102633,
        1.400337030681838,
        -3.8724412503669834,
        -2.6501765590300543,
        -3.9242348225173718,
        2.327917165843603,
        4.599161424003572,
        -3.2029832724123675,
        4.085723954062923,
        -2.1725763994943637,
        2.2769129064726448,
        4.539106340417371,
        -4.506589051449553,
        1.3324153035110005,
        1.0881133449400373,
        2.4920981692291777,
        3.207604204305719,
        2.1903384477732137,
        3.6209006343663273,
        4.2359580675856385,
        4.304261934866787,
        -2.590717494754137,
        3.175926182657049,
        -1.6966466732374377,
        -4.700877951471996,
        3.34717811846987
    ],
    "label": {
        "x": [
            0.0,
            1.0,
            0.0,
            0.0,
            0.0,
            1.0,
            0.0,
            0.0,
            1.0,
            0.0,
            0.0,
            0.0
        ],
        "z": [
            -1.0,
            1.0,
            -1.0,
            -1.0,
            -1.0,
            1.0,
            -1.0,
            -1.0,
            1.0,
            -1.0,
            -1.0,
            -1.0
        ],
        "obj_val": -78.11238093531632
    }
}